pythonvideoannotator_module_idtrackerai/__init__.py
pythonvideoannotator_module_idtrackerai/__main__.py
pythonvideoannotator_module_idtrackerai/constants.py
pythonvideoannotator_module_idtrackerai/idtrackerai_importer.py
pythonvideoannotator_module_idtrackerai/module.py
pythonvideoannotator_module_idtrackerai/settings.py
pythonvideoannotator_module_idtrackerai/utils.py
pythonvideoannotator_module_idtrackerai/models/__init__.py
pythonvideoannotator_module_idtrackerai/models/project_idtrackerai.py
pythonvideoannotator_module_idtrackerai/models/video/__init__.py
pythonvideoannotator_module_idtrackerai/models/video/video_idtrackerai.py
pythonvideoannotator_module_idtrackerai/models/video/objects/__init__.py
pythonvideoannotator_module_idtrackerai/models/video/objects/idtrackerai_object.py
pythonvideoannotator_module_idtrackerai/models/video/objects/idtrackerai_object_io.py
pythonvideoannotator_module_idtrackerai/models/video/objects/idtrackerai_object_mouse_events.py
pythonvideoannotator_module_idtrackerai/models/video/objects/object2d/__init__.py
pythonvideoannotator_module_idtrackerai/models/video/objects/object2d/object2d_idtrackerai.py
pythonvideoannotator_module_idtrackerai/models/video/objects/object2d/datasets/__init__.py
pythonvideoannotator_module_idtrackerai/models/video/objects/object2d/datasets/path/__init__.py
pythonvideoannotator_module_idtrackerai/models/video/objects/object2d/datasets/path/path_idtrackerai.py
pythonvideoannotator_module_idtrackerai/models/video/objects/object2d/datasets/path/sel_object_win.py
Python_video_annotator_module_IdTrackerAI_shaliulab-1.0.9.dist-info/METADATA
Python_video_annotator_module_IdTrackerAI_shaliulab-1.0.9.dist-info/WHEEL
Python_video_annotator_module_IdTrackerAI_shaliulab-1.0.9.dist-info/entry_points.txt
Python_video_annotator_module_IdTrackerAI_shaliulab-1.0.9.dist-info/top_level.txt
Python_video_annotator_module_IdTrackerAI_shaliulab-1.0.9.dist-info/RECORD
