Metadata-Version: 2.1
Name: Python-video-annotator-module-IdTrackerAI-shaliulab
Version: 1.0.9
Home-page: https://github.com/UmSenhorQualquer/pythonvideoannotator-module-idtrackerai
Author: ['Ricardo Ribeiro']
Author-email: ricardojvr@gmail.com
Provides-Extra: imgstore
Requires-Dist: imgstore-shaliulab (>=0.4.4) ; extra == 'imgstore'
